func_ai/__init__.py
func_ai/function_indexer.py
func_ai/ui_demos/__init__.py
func_ai/ui_demos/api_qa.py
func_ai/utils/__init__.py
func_ai/utils/api_qa_system_prompt.txt
func_ai/utils/common.py
func_ai/utils/jinja_template_functions.py
func_ai/utils/llm_tools.py
func_ai/utils/openapi_function_parser.py
func_ai/utils/py_function_parser.py
func_ai/workflow_creator.py
func_ai-0.0.14.dist-info/LICENSE
func_ai-0.0.14.dist-info/METADATA
func_ai-0.0.14.dist-info/WHEEL
func_ai-0.0.14.dist-info/RECORD
