Metadata-Version: 2.1
Name: func-ai
Version: 0.0.14
Summary: AI Functional Catalog - OpenAI functions on steriods
License: MIT
Author: Trayan Azarov
Author-email: trayan.azarov@amikos.tech
Requires-Python: >=3.10,<4.0
Classifier: License :: OSI Approved :: MIT License
Classifier: Programming Language :: Python :: 3
Classifier: Programming Language :: Python :: 3.10
Classifier: Programming Language :: Python :: 3.11
Requires-Dist: chromadb (>=0.4.2,<0.5.0)
Requires-Dist: gradio (>=3.36.1,<4.0.0)
Requires-Dist: jinja2 (>=3.1.2,<4.0.0)
Requires-Dist: jsonschema (>=4.18.0,<5.0.0)
Requires-Dist: openai (>=0.27.8,<0.28.0)
Requires-Dist: python-dotenv (>=1.0.0,<2.0.0)
Requires-Dist: pyyaml (>=6.0,<7.0)
Requires-Dist: requests (>=2.31.0,<3.0.0)
Requires-Dist: tenacity (>=8.2.2,<9.0.0)
Requires-Dist: torch (>=2.0.1,<3.0.0)
Requires-Dist: transformers (>=4.30.2,<5.0.0)
Project-URL: Bug Tracker, https://github.com/amikos-tech/func-ai/issues
Project-URL: Homepage, https://github.com/amikos-tech/func-ai/
Project-URL: Source, https://github.com/amikos-tech/func-ai/
